Metadata-Version: 1.0
Name: SimpleUpload
Version: 0.1.0
Summary: A HTTP Server for upload file.
Home-page: https://github.com/codeif/SimpleUpload
Author: codeif
Author-email: me@codeif.com
License: MIT
Platform: UNKNOWN
